tagsub/Template.py
tagsub/__init__.py
tagsub/constants.py
tagsub/exceptions/__init__.py
tagsub/tags/CaseTag.py
tagsub/tags/ElifTag.py
tagsub/tags/ElseTag.py
tagsub/tags/IfTag.py
tagsub/tags/IfTagContainer.py
tagsub/tags/LoopTag.py
tagsub/tags/NamespaceTag.py
tagsub/tags/NullTag.py
tagsub/tags/OptionTag.py
tagsub/tags/RootTag.py
tagsub/tags/SaveEvalTag.py
tagsub/tags/SaveOverrideTag.py
tagsub/tags/SaveRawTag.py
tagsub/tags/SimpleTag.py
tagsub/tags/SuperTag.py
tagsub/tags/Tag.py
tagsub/tags/TagAlternateChoice.py
tagsub/tags/TagContainer.py
tagsub/tags/__init__.py
tagsub/tags/text/CommentNode.py
tagsub/tags/text/TagsubCommentNode.py
tagsub/tags/text/TextNode.py
tagsub/tags/text/__init__.py
tagsub/tags/values/AndOperator.py
tagsub/tags/values/ConstantValue.py
tagsub/tags/values/ExpressionParser.py
tagsub/tags/values/NotOperator.py
tagsub/tags/values/Operator.py
tagsub/tags/values/OrOperator.py
tagsub/tags/values/Token.py
tagsub/tags/values/Value.py
tagsub/tags/values/__init__.py
tagsub/util/Stack.py
tagsub/util/__init__.py
tagsub3-1.68.dist-info/LICENSE
tagsub3-1.68.dist-info/METADATA
tagsub3-1.68.dist-info/WHEEL
tagsub3-1.68.dist-info/top_level.txt
tagsub3-1.68.dist-info/RECORD
