Metadata-Version: 2.1
Name: tagsub3
Version: 1.68
Summary: tagsub template formatting package
Home-page: http://www.shawndyer.com/
Author: Shawn Dyer
Author-email: sdyer@dyermail.net
License: UNKNOWN
Platform: UNKNOWN
Classifier: Programming Language :: Python :: 3
Classifier: License :: OSI Approved :: MIT License
Classifier: Operating System :: OS Independent
Requires-Python: >=3.8
